Metadata-Version: 2.1
Name: devyl
Version: 0.0.6
Summary: Metrics evaluation for binary classification model
Home-page: https://github.com/devyratnasari/devyl
Author: Devy Ratnasari
Author-email: imthedevyl@gmail.com
License: MIT
Keywords: metrics
Platform: UNKNOWN
Classifier: Development Status :: 5 - Production/Stable
Classifier: Intended Audience :: Education
Classifier: Operating System :: Microsoft :: Windows :: Windows 10
Classifier: License :: OSI Approved :: MIT License
Classifier: Programming Language :: Python :: 3
License-File: LICENSE.txt
